__init__.py
subatomic_agents/__init__.py
subatomic_agents/errors/__init__.py
subatomic_agents/errors/document_loader_errors.py
subatomic_agents/helpers/__init__.py
subatomic_agents/helpers/document_loaders.py
subatomic_agents/helpers/file_types.py
subatomic_agents/helpers/files_and_folders.py
subatomic_agents/helpers/helper_github.py
subatomic_agents/helpers/helper_react_agents.py
subatomic_agents/helpers/outputs/__init__.py
subatomic_agents/helpers/outputs/general_outputs.py
subatomic_agents/helpers/outputs/sales_proposal_outputs.py
subatomic_agents/react_agent_architecture/__init__.py
subatomic_agents/react_agent_architecture/react_agent_architecture.py
subatomic_agents/sales_proposal/__init__.py
subatomic_agents/sales_proposal/agents/__init__.py
subatomic_agents/sales_proposal/agents/invoke_sales_proposal_agent.py
subatomic_agents/sales_proposal/agents/sales_proposal_graph_tool.py
subatomic_agents/sales_proposal/factories/__init__.py
subatomic_agents/sales_proposal/factories/config_factory.py
subatomic_agents/sales_proposal/models/__init__.py
subatomic_agents/sales_proposal/models/input_schema.py
subatomic_agents/sales_proposal/services/__init__.py
subatomic_agents/sales_proposal/services/agentic_generator.py
subatomic_agents/sales_proposal/services/generator.py
subatomic_agents/static/subatomic_footer.png
subatomic_agents/static/css_for_pdf_formats/sales_proposal.css
subatomic_agents-0.1.7.1.dist-info/METADATA
subatomic_agents-0.1.7.1.dist-info/WHEEL
subatomic_agents-0.1.7.1.dist-info/top_level.txt
subatomic_agents-0.1.7.1.dist-info/RECORD
